{
 "HEADLINE": "Hello da!",
 "LANG_DE": "Deutsch",
 "LANG_EN": "English",
 "LANG_FR": "Français",
 "Impressum": "Impressum",
 "Übersicht": "Übersicht",
 "KSym_Erf": "Kernsymptome erfassen",
 "Frageb": "Fragebögen",
 "Uebung_Durchf": "Übungen durchführen",
 "Route": "Route",
 "Z-S": "Zahlen-Symbol",
 "Motorik": "Motorik",
 "Q1core": "Sind Sie Rechtshänder?",
 "Q2core": "Haben Sie eine Bewegungseinschränkung in der rechten/linken Hand?",
 "Q3core": "Haben Sie eine Gefühlsstörung in der rechten/linken Hand?",
 "Q4core": "Wie fühlen Sie sich heute?",
 "Q5core": "Wie beurteilen Sie ihre momentane Konzentrationsfähigkeit?",
 "Q6core": "Hatten Sie seit der letzen Übung einen Schub?",
 "Q7core": "Haben Ihre MS Symptome seit der letzten Übung zugenommen?",
 "yes":"Ja",
 "no":"Nein",
 "save":"Speichern",
 "MsisQs1" : "Wie sehr waren sie in den letzen 2 Wochen eingeschränkt…",
 "MsisQs2" : "Wie sehr waren sie in den letzen 2 Wochen beeinträchtigt durch...",
 "Msis":{
   "Radios":[
      {"id": "1", "label": "gar nicht"},
      {"id": "2", "label": "ein bisschen"},
      {"id": "3", "label": "mässig"},
      {"id": "4", "label": "ziemlich"},
      {"id": "5", "label": "sehr"}
    ],
   "Questions1":[
     {"id": "1", "text": "körperlich anstrengende Dinge zu tun?"},
     {"id": "2", "text": "Dinge fest anzufassen (z.B. Hahn aufdrehen)?"},
     {"id": "3", "text": "Dinge zu tragen?"}
   ],
   "Questions2":[
     {"id": "1", "text": "Probleme mit dem Gleichgewicht?"},
     {"id": "2", "text": "Schwierigkeiten, sich in der Wohnung zu bewegen?"},
     {"id": "3", "text": "ungeschickt zu sein?"},
     {"id": "4", "text": "steif zu sein"},
     {"id": "5", "text": "schwere Arme und/oder Beine zu haben?"}
   ],
 "Questions3":[
   {"id": "1", "text": "Zittern der Arme oder Beine zu haben?"},
   {"id": "2", "text": "Krämpfe der Extremitäten zu haben?"},
   {"id": "3", "text": "dass ihr Körper nicht tat, was sie wollten?"},
   {"id": "4", "text": "dass sie davon abhingen, dass Andere Dinge für sie erledigten?"},
   {"id": "5", "text": "Beeinträchtigung im sozialen und Freizeitleben zu Hause?"},
   {"id": "6", "text": "gezwungen zu sein, zu Hause zu bleiben?"},
   {"id": "7", "text": "Probleme der Hände bei Alltagstätigkeiten?"},
   {"id": "8", "text": "die Zeit für Arbeit oder Alltagsaktivitäten einzuschränken?"},
   {"id": "9", "text": "Probleme sich fortzubewegen (Auto, Bus, Taxis,Zug)?"},
   {"id": "10", "text": "länger für Dinge zu brauchen?"}
 ],
 "Questions4":[
   {"id": "1", "text": "Schwierigkeiten, Dinge spontan zu machen?"},
   {"id": "2", "text": "ganz schnell zur Toilette zu müssen?"},
   {"id": "3", "text": "sich allgemein unwohl zu fühlen?"},
   {"id": "4", "text": "Schlafprobleme zu haben?"},
   {"id": "5", "text": "sich geistig/mental müde zu fühlen?"},
   {"id": "6", "text": "Sorgen bezogen auf MS zu haben?"},
   {"id": "7", "text": "sich angespannt und ängstlich zu fühlen?"},
   {"id": "8", "text": "sich störbar, ungeduldig und aufbrausend zu fühlen?"},
   {"id": "9", "text": "Konzentrationsprobleme zu haben?"},
   {"id": "10", "text": "keine Zuversicht zu haben?"},
   {"id": "11", "text": "sich traurig/depressiv zu fühlen?"}
 ]
 }
}
